{"clues": {"across": [{"key": 1, "hint": "Sound from a donkey"}, {"key": 5, "hint": "Freezing point of water on the Celsius scale"}, {"key": 6, "hint": "Orangutan doctor in \"Planet of the Apes\""}, {"key": 8, "hint": "Country south of Ecuador"}, {"key": 9, "hint": "Toy on a snow day"}], "down": [{"key": 1, "hint": "Sound from a bee"}, {"key": 2, "hint": "Harvests"}, {"key": 3, "hint": "Disney character with a seashell bikini top"}, {"key": 4, "hint": "\"___ one to talk!\""}, {"key": 7, "hint": "French for ''south\""}]}, "cells": [{"id": 0, "key": 1, "letter": "B"}, {"id": 1, "key": 2, "letter": "R"}, {"id": 2, "key": 3, "letter": "A"}, {"id": 3, "key": 4, "letter": "Y"}, {"id": 4, "key": null, "letter": null}, {"id": 5, "key": 5, "letter": "Z"}, {"id": 6, "key": null, "letter": "E"}, {"id": 7, "key": null, "letter": "R"}, {"id": 8, "key": null, "letter": "O"}, {"id": 9, "key": null, "letter": null}, {"id": 10, "key": 6, "letter": "Z"}, {"id": 11, "key": null, "letter": "A"}, {"id": 12, "key": null, "letter": "I"}, {"id": 13, "key": null, "letter": "U"}, {"id": 14, "key": 7, "letter": "S"}, {"id": 15, "key": null, "letter": null}, {"id": 16, "key": 8, "letter": "P"}, {"id": 17, "key": null, "letter": "E"}, {"id": 18, "key": null, "letter": "R"}, {"id": 19, "key": null, "letter": "U"}, {"id": 20, "key": null, "letter": null}, {"id": 21, "key": 9, "letter": "S"}, {"id": 22, "key": null, "letter": "L"}, {"id": 23, "key": null, "letter": "E"}, {"id": 24, "key": null, "letter": "D"}]}