{"clues": {"across": [{"key": 1, "hint": "Trivial entertainment"}, {"key": 6, "hint": "Opposite of a social butterfly"}, {"key": 7, "hint": "Closing part of a song"}, {"key": 8, "hint": "Taking advantage of"}, {"key": 9, "hint": "Salinger's \"The Catcher in the ___\""}], "down": [{"key": 1, "hint": "Ingredient in dough"}, {"key": 2, "hint": "Terrible"}, {"key": 3, "hint": "Loosen, as shoelaces"}, {"key": 4, "hint": "Plant with fronds"}, {"key": 5, "hint": "Rain forest croaker"}]}, "cells": [{"id": 0, "key": 1, "letter": "F"}, {"id": 1, "key": 2, "letter": "L"}, {"id": 2, "key": 3, "letter": "U"}, {"id": 3, "key": 4, "letter": "F"}, {"id": 4, "key": 5, "letter": "F"}, {"id": 5, "key": 6, "letter": "L"}, {"id": 6, "key": null, "letter": "O"}, {"id": 7, "key": null, "letter": "N"}, {"id": 8, "key": null, "letter": "E"}, {"id": 9, "key": null, "letter": "R"}, {"id": 10, "key": 7, "letter": "O"}, {"id": 11, "key": null, "letter": "U"}, {"id": 12, "key": null, "letter": "T"}, {"id": 13, "key": null, "letter": "R"}, {"id": 14, "key": null, "letter": "O"}, {"id": 15, "key": 8, "letter": "U"}, {"id": 16, "key": null, "letter": "S"}, {"id": 17, "key": null, "letter": "I"}, {"id": 18, "key": null, "letter": "N"}, {"id": 19, "key": null, "letter": "G"}, {"id": 20, "key": 9, "letter": "R"}, {"id": 21, "key": null, "letter": "Y"}, {"id": 22, "key": null, "letter": "E"}, {"id": 23, "key": null, "letter": null}, {"id": 24, "key": null, "letter": null}]}